wirerope/__init__.py
wirerope/_compat.py
wirerope/_util.py
wirerope/_version.py
wirerope/callable.py
wirerope/rope.py
wirerope/wire.py
wirerope-0.4.8.dist-info/LICENSE
wirerope-0.4.8.dist-info/METADATA
wirerope-0.4.8.dist-info/WHEEL
wirerope-0.4.8.dist-info/top_level.txt
wirerope-0.4.8.dist-info/RECORD
