Metadata-Version: 2.1
Name: wirerope
Version: 0.4.8
Summary: 'Turn functions and methods into fully controllable objects'
Home-page: https://github.com/youknowone/wirerope
Author: Jeong YunWon
Author-email: wirerope@youknowone.org
License: BSD 2-Clause License
Keywords: ring,methodtools,hack,method
Classifier: License :: OSI Approved :: BSD License
Classifier: Programming Language :: Python :: 2
Classifier: Programming Language :: Python :: 2.7
Classifier: Programming Language :: Python :: 3
Classifier: Programming Language :: Python :: 3.4
Classifier: Programming Language :: Python :: 3.5
Classifier: Programming Language :: Python :: 3.6
Classifier: Programming Language :: Python :: 3.7
Classifier: Programming Language :: Python :: 3.8
Classifier: Programming Language :: Python :: 3.9
Classifier: Programming Language :: Python :: 3.10
Classifier: Programming Language :: Python :: 3.11
Classifier: Programming Language :: Python :: 3.12
Classifier: Programming Language :: Python :: 3.13
License-File: LICENSE
Requires-Dist: six>=1.11.0
Requires-Dist: inspect2>=0.1.0; python_version < "3"
Requires-Dist: singledispatch>=3.4.0.3; python_version < "3.4"
Provides-Extra: test
Requires-Dist: pytest>=4.6.7; extra == "test"
Requires-Dist: pytest-cov>=2.6.1; extra == "test"
Requires-Dist: pytest-checkdocs>=1.2.5; python_version < "3" and extra == "test"
Requires-Dist: pytest-checkdocs>=2.9.0; python_version >= "3" and extra == "test"
Provides-Extra: doc
Requires-Dist: sphinx; extra == "doc"
